TooMuchPython/__init__.py
TooMuchPython-0.0.2.dist-info/LICENSE
TooMuchPython-0.0.2.dist-info/METADATA
TooMuchPython-0.0.2.dist-info/WHEEL
TooMuchPython-0.0.2.dist-info/top_level.txt
TooMuchPython-0.0.2.dist-info/RECORD
