Metadata-Version: 2.1
Name: TooMuchPython
Version: 0.0.2
Summary: Too much Python or tmp
Home-page: https://github.com/Mankifg/TooMuchPython
Author: Mankifg
Author-email: mankifg@gmail.com
Project-URL: Bug Tracker, https://github.com/Mankifg/TooMuchPython/issues
Classifier: Programming Language :: Python :: 3
Classifier: License :: OSI Approved :: MIT License
Classifier: Operating System :: OS Independent
Requires-Python: >=3.6
License-File: LICENSE
